{
  "events": [
    {
      "id": "parti_liderligi",
      "title": "Parti Liderliği",
      "description": "Adalet ve Kalkınma Partisi (AKP) yaklaşan seçimlere katılmak için güçlü bir lidere ihtiyaç duyuyor. Partiyi yönetmek için öne çıkacak mısınız?",
      "era": "iktidara_yukselis",
      "yesImpact": {
        "health": -5,
        "wealth": 0,
        "political": 15,
        "communal": 10,
        "optionText": "AKP'yi zafere taşıyacağım"
      },
      "noImpact": {
        "health": 0,
        "wealth": 0,
        "political": -10,
        "communal": 5,
        "optionText": "Perde arkasından destek vereceğim"
      },
      "yesChainEventId": "secim_zaferi",
      "noChainEventId": null,
      "imagePath": "assets/events/Party Leadership.jpeg",
      "sequence": 1
    },
    {
      "id": "secim_zaferi",
      "title": "Seçim Zaferi",
      "description": "Partiniz seçimleri kazandı! Lider olarak, Başbakan olma konumundasınız. Hemen büyük reformlar için harekete geçecek misiniz?",
      "era": "iktidara_yukselis",
      "yesImpact": {
        "health": 0,
        "wealth": 5,
        "political": 10,
        "communal": -5,
        "optionText": "Türkiye'nin acil değişime ihtiyacı var"
      },
      "noImpact": {
        "health": 0,
        "wealth": 0,
        "political": -5,
        "communal": 10,
        "optionText": "Temkinli hareket etmeliyiz"
      },
      "yesChainEventId": "ab_uyelik_gorusmeleri",
      "noChainEventId": null,
      "imagePath": "assets/events/Election Victory.jpeg",
      "sequence": 2
    },
    {
      "id": "askeri_etki",
      "title": "Askeri Etki",
      "description": "Ordu hala Türk siyasetinde önemli bir etkiye sahip. Güçlerini azaltmak için adımlar atacak mısınız?",
      "era": "iktidara_yukselis",
      "yesImpact": {
        "health": 0,
        "wealth": 0,
        "political": 15,
        "communal": -10,
        "optionText": "Sivil kontrol sağlanmalıdır"
      },
      "noImpact": {
        "health": 0,
        "wealth": 0,
        "political": -5,
        "communal": 5,
        "optionText": "Şimdilik orduyla çalışalım"
      },
      "yesChainEventId": "ergenekon_davasi",
      "noChainEventId": null,
      "imagePath": "assets/events/Military Influence.jpeg",
      "sequence": 3
    },
    {
      "id": "basortusu_yasagi",
      "title": "Başörtüsü Yasağı",
      "description": "Kamu kurumlarında başörtüsü yasağı tartışmalı bir konu. Destekçilerinizin çoğu bu yasağın kaldırılmasını istiyor. Bu yasağı kaldırmak için harekete geçecek misiniz?",
      "era": "iktidara_yukselis",
      "yesImpact": {
        "health": 0,
        "wealth": 0,
        "political": 5,
        "communal": 5,
        "optionText": "Bu yasak dini özgürlükleri ihlal ediyor"
      },
      "noImpact": {
        "health": 0,
        "wealth": 0,
        "political": -10,
        "communal": -10,
        "optionText": "Şimdi bu konuyu ele almanın zamanı değil"
      },
      "yesChainEventId": "laik_protestolar",
      "noChainEventId": null,
      "imagePath": "assets/events/Headscarf Ban.jpeg",
      "sequence": 4
    },
    {
      "id": "ab_uyelik_gorusmeleri",
      "title": "AB Üyelik Görüşmeleri",
      "description": "Avrupa Birliği, Türkiye ile üyelik görüşmelerini açmayı düşünüyor. Gerekli demokratik reformları uygulayacak mısınız?",
      "era": "iktidara_yukselis",
      "yesImpact": {
        "health": 0,
        "wealth": 15,
        "political": 10,
        "communal": -5,
        "optionText": "AB standartlarını karşılayacağız"
      },
      "noImpact": {
        "health": 0,
        "wealth": -10,
        "political": 5,
        "communal": 10,
        "optionText": "Egemenliğimizden taviz vermeyeceğiz"
      },
      "yesChainEventId": "ekonomik_buyume",
      "noChainEventId": null,
      "imagePath": "assets/events/EU Membership Negotiations.jpeg",
      "sequence": 5
    },
    {
      "id": "gulen_ittifaki",
      "title": "Gülen İttifakı",
      "description": "Gülen hareketi hükümetinize destek sunuyor. Ağları eğitim, medya ve yargıyı kapsıyor. Onlarla bir ittifak kuracak mısınız?",
      "era": "konsolidasyon",
      "yesImpact": {
        "health": 0,
        "wealth": 0,
        "political": 20,
        "communal": 10,
        "optionText": "Destekleri Türkiye'yi dönüştürmemize yardımcı olacak"
      },
      "noImpact": {
        "health": 0,
        "wealth": 0,
        "political": -15,
        "communal": -5,
        "optionText": "Bağımsızlığımızı korumalıyız"
      },
      "yesChainEventId": "gulen_etkisi",
      "noChainEventId": null,
      "imagePath": "assets/events/Gulen Alliance.jpeg",
      "sequence": 10
    },
    {
      "id": "gezi_parki_protestolari",
      "title": "Gezi Parkı Protestoları",
      "description": "Protestocular kentsel gelişim planlarınıza karşı İstanbul'daki Gezi Parkı'nı işgal ediyor. Protestolar ülke çapında yayılıyor. Parkı zorla boşaltacak mısınız?",
      "era": "konsolidasyon",
      "yesImpact": {
        "health": -10,
        "wealth": 0,
        "political": 10,
        "communal": -20,
        "optionText": "Kanunsuzluğa izin vermeyeceğiz"
      },
      "noImpact": {
        "health": 0,
        "wealth": 0,
        "political": -15,
        "communal": 10,
        "optionText": "Endişelerini dinleyelim"
      },
      "yesChainEventId": "uluslararasi_elestiri",
      "noChainEventId": null,
      "imagePath": "assets/events/Gezi Park Protests.jpeg",
      "sequence": 17
    },
    {
      "id": "kurt_baris_sureci",
      "title": "Kürt Barış Süreci",
      "description": "Kürt gruplarla barış görüşmelerine başlama fırsatı var. Resmi bir barış süreci başlatacak mısınız?",
      "era": "konsolidasyon",
      "yesImpact": {
        "health": 10,
        "wealth": 0,
        "political": -10,
        "communal": 20,
        "optionText": "Bu çatışmayı diyalog yoluyla sonlandırma zamanı geldi"
      },
      "noImpact": {
        "health": 0,
        "wealth": 0,
        "political": 10,
        "communal": -15,
        "optionText": "Teröristlerle müzakere etmeyeceğiz"
      },
      "yesChainEventId": "baris_muzakereleri",
      "noChainEventId": "pkk_catisma_tirmandirma",
      "imagePath": "assets/events/Kurdish Peace Process.jpeg",
      "sequence": 12
    },
    {
      "id": "suriye_ic_savasi",
      "title": "Suriye İç Savaşı",
      "description": "Suriye'de iç savaş patlak verdi. Esad rejimine karşı muhalif grupları destekleyecek misiniz?",
      "era": "konsolidasyon",
      "yesImpact": {
        "health": 0,
        "wealth": -10,
        "political": 10,
        "communal": 5,
        "optionText": "Esad gitmeli"
      },
      "noImpact": {
        "health": 0,
        "wealth": 5,
        "political": -5,
        "communal": -5,
        "optionText": "Türkiye tarafsız kalmalı"
      },
      "yesChainEventId": "suriyeli_multeci_krizi",
      "noChainEventId": null,
      "imagePath": "assets/events/Syrian Civil War.jpeg",
      "sequence": 14
    },
    {
      "id": "ekonomik_buyume",
      "title": "Ekonomik Büyüme",
      "description": "Türkiye ekonomisi hızla büyüyor. Büyük altyapı projelerine (yeni havalimanı, köprüler vb.) yatırım yapacak mısınız?",
      "era": "konsolidasyon",
      "yesImpact": {
        "health": 0,
        "wealth": -10,
        "political": 15,
        "communal": 10,
        "optionText": "Bu projeler Türkiye'yi dönüştürecek"
      },
      "noImpact": {
        "health": 0,
        "wealth": 15,
        "political": -10,
        "communal": -5,
        "optionText": "Sürdürülebilir büyümeye odaklanmalıyız"
      },
      "yesChainEventId": "mega_projeler",
      "noChainEventId": null,
      "imagePath": "assets/events/Economic Growth.jpeg",
      "sequence": 16
    },
    {
      "id": "gulen_etkisi",
      "title": "Gülen Etkisi",
      "description": "Gülen hareketi devlet kurumlarında önemli bir etki kazandı. İstihbarat raporları 'paralel devlet' oluşturduklarını öne sürüyor. Onlara karşı harekete geçecek misiniz?",
      "era": "kriz_ve_tepki",
      "yesImpact": {
        "health": 0,
        "wealth": 0,
        "political": -10,
        "communal": -15,
        "optionText": "Bu tehdidi temizlemeliyiz"
      },
      "noImpact": {
        "health": 0,
        "wealth": 0,
        "political": 5,
        "communal": 0,
        "optionText": "Bunlar sadece söylenti"
      },
      "yesChainEventId": "darbe_girisimi",
      "noChainEventId": "darbe_girisimi",
      "imagePath": "assets/events/Gulen Influence.jpeg",
      "sequence": 20
    },
    {
      "id": "baris_pinari_harekati",
      "title": "Barış Pınarı Harekatı",
      "description": "Suriye'nin kuzeyindeki YPG/PKK unsurlarına karşı sınır ötesi askeri operasyon başlatma planları hazır. Bu operasyonu onaylayacak mısınız?",
      "era": "kriz_ve_tepki",
      "yesImpact": {
        "health": -10,
        "wealth": -15,
        "political": 20,
        "communal": 15,
        "optionText": "Sınır güvenliğimiz için operasyon başlatılmalı"
      },
      "noImpact": {
        "health": 5,
        "wealth": 10,
        "political": -15,
        "communal": -10,
        "optionText": "Diplomatik çözüm arayışına devam edelim"
      },
      "yesChainEventId": "uluslararasi_yaptirimlar",
      "noChainEventId": "sinir_guvenligi_tehdidi",
      "imagePath": "assets/events/Peace Spring Operation.jpeg",
      "sequence": 23,
      "isNeutralEvent": false
    },
    {
      "id": "papaz_brunson_krizi",
      "title": "Papaz Brunson Krizi",
      "description": "Amerikalı Papaz Andrew Brunson darbe girişimiyle bağlantılı olarak tutuklandı. ABD, serbest bırakılması için baskı yapıyor ve yaptırımlarla tehdit ediyor. Papazı serbest bırakacak mısınız?",
      "era": "kriz_ve_tepki",
      "yesImpact": {
        "health": 0,
        "wealth": 15,
        "political": -10,
        "communal": -5,
        "optionText": "ABD ile ilişkilerimizi korumak için serbest bırakalım"
      },
      "noImpact": {
        "health": 0,
        "wealth": -20,
        "political": 15,
        "communal": 10,
        "optionText": "Yargı bağımsızlığına müdahale etmeyeceğiz"
      },
      "yesChainEventId": "abd_iliskileri_iyilesme",
      "noChainEventId": "abd_yaptirimlari",
      "imagePath": "assets/events/Pastor Brunson Crisis.jpeg",
      "sequence": 24,
      "isNeutralEvent": false
    },
    {
      "id": "s400_fuze_sistemi",
      "title": "S-400 Füze Sistemi",
      "description": "Rusya'dan S-400 hava savunma sistemleri satın alma fırsatınız var. NATO müttefikleriniz, özellikle ABD, buna karşı çıkıyor. Satın almayı onaylayacak mısınız?",
      "era": "kriz_ve_tepki",
      "yesImpact": {
        "health": 0,
        "wealth": -15,
        "political": 20,
        "communal": 15,
        "optionText": "Ulusal güvenliğimiz için S-400'leri alacağız"
      },
      "noImpact": {
        "health": 0,
        "wealth": 10,
        "political": -15,
        "communal": -10,
        "optionText": "NATO müttefiklerimizle ilişkilerimizi koruyacağız"
      },
      "yesChainEventId": "f35_programindan_cikarilma",
      "noChainEventId": null,
      "imagePath": "assets/events/S-400 Missile System.jpeg",
      "sequence": 26,
      "isNeutralEvent": false
    },
    {
      "id": "merkez_bankasi_baskani_degisimi",
      "title": "Merkez Bankası Başkanı Değişimi",
      "description": "Merkez Bankası Başkanı faiz politikalarınızla uyuşmazlık yaşıyor. Başkanı görevden alacak mısınız?",
      "era": "kriz_ve_tepki",
      "yesImpact": {
        "health": 0,
        "wealth": -20,
        "political": 15,
        "communal": -5,
        "optionText": "Ekonomi politikalarımızla uyumlu bir başkan atayacağız"
      },
      "noImpact": {
        "health": 0,
        "wealth": 15,
        "political": -10,
        "communal": 5,
        "optionText": "Merkez Bankası'nın bağımsızlığına saygı göstereceğiz"
      },
      "yesChainEventId": "yatirimci_guven_kaybi",
      "noChainEventId": null,
      "imagePath": "assets/events/Central Bank Governor Change.jpeg",
      "sequence": 28,
      "isNeutralEvent": false
    },
    {
      "id": "dogu_akdeniz_gerginligi",
      "title": "Doğu Akdeniz Gerginliği",
      "description": "Doğu Akdeniz'de doğal gaz arama çalışmaları Yunanistan ve Güney Kıbrıs ile gerginliğe yol açıyor. Sismik araştırma gemilerinizi bölgeye gönderecek misiniz?",
      "era": "kriz_ve_tepki",
      "yesImpact": {
        "health": 0,
        "wealth": -10,
        "political": 20,
        "communal": 15,
        "optionText": "Mavi Vatan'daki haklarımızı savunacağız"
      },
      "noImpact": {
        "health": 0,
        "wealth": 10,
        "political": -15,
        "communal": -10,
        "optionText": "Diplomatik çözüm için müzakerelere odaklanacağız"
      },
      "yesChainEventId": "ab_yaptirimlari",
      "noChainEventId": null,
      "imagePath": "assets/events/Eastern Mediterranean Tension.jpeg",
      "sequence": 29,
      "isNeutralEvent": false
    },
    {
      "id": "ohal_uzatma_karari",
      "title": "OHAL Uzatma Kararı",
      "description": "Darbe girişimi sonrası ilan edilen OHAL'in süresi doluyor. OHAL'i uzatacak mısınız?",
      "era": "kriz_ve_tepki",
      "yesImpact": {
        "health": -5,
        "wealth": -5,
        "political": 20,
        "communal": -15,
        "optionText": "Güvenlik tehditleri devam ediyor, OHAL uzatılmalı"
      },
      "noImpact": {
        "health": 5,
        "wealth": 10,
        "political": -10,
        "communal": 15,
        "optionText": "Normal demokratik düzene dönme zamanı geldi"
      },
      "yesChainEventId": "uluslararasi_insan_haklari_elestirisi",
      "noChainEventId": null,
      "imagePath": "assets/events/State of Emergency Extension.jpeg",
      "sequence": 23,
      "isNeutralEvent": false
    },
    {
      "id": "suriyeli_multeci_politikasi",
      "title": "Suriyeli Mülteci Politikası",
      "description": "Türkiye'de 3.5 milyondan fazla Suriyeli mülteci var ve toplumsal tepkiler artıyor. Mültecilerin Avrupa'ya geçişine izin verecek misiniz?",
      "era": "kriz_ve_tepki",
      "yesImpact": {
        "health": -5,
        "wealth": 10,
        "political": 15,
        "communal": 10,
        "optionText": "Avrupa sınırlarını açacağız"
      },
      "noImpact": {
        "health": -10,
        "wealth": -15,
        "political": -10,
        "communal": -5,
        "optionText": "AB anlaşmasına bağlı kalacağız"
      },
      "yesChainEventId": "ab_multeci_anlasmasi_krizi",
      "noChainEventId": null,
      "imagePath": "assets/events/Syrian Refugee Policy.jpeg",
      "sequence": 26,
      "isNeutralEvent": false
    },
    {
      "id": "idlib_operasyonu",
      "title": "İdlib Operasyonu",
      "description": "Suriye'nin İdlib kentinde Esad rejimi ilerliyor ve Türk gözlem noktaları tehdit altında. Askeri müdahalede bulunacak mısınız?",
      "era": "kriz_ve_tepki",
      "yesImpact": {
        "health": -15,
        "wealth": -10,
        "political": 20,
        "communal": 15,
        "optionText": "Askerlerimizi ve sivilleri korumak için operasyon başlatacağız"
      },
      "noImpact": {
        "health": 0,
        "wealth": 5,
        "political": -15,
        "communal": -10,
        "optionText": "Rusya ile diplomatik çözüm arayacağız"
      },
      "yesChainEventId": "rusya_ile_gerginlik",
      "noChainEventId": "gozlem_noktalari_kaybi",
      "imagePath": "assets/events/Idlib Operation.jpeg",
      "sequence": 27,
      "isNeutralEvent": false
    },
    {
      "id": "kanal_istanbul_projesi",
      "title": "Kanal İstanbul Projesi",
      "description": "İstanbul Boğazı'na alternatif olarak yapay bir su yolu projesi olan Kanal İstanbul'u başlatacak mısınız?",
      "era": "kriz_ve_tepki",
      "yesImpact": {
        "health": -10,
        "wealth": -20,
        "political": 15,
        "communal": -15,
        "optionText": "Bu proje Türkiye'nin prestij projesi olacak"
      },
      "noImpact": {
        "health": 5,
        "wealth": 10,
        "political": -10,
        "communal": 15,
        "optionText": "Çevresel ve ekonomik kaygılar nedeniyle erteleyeceğiz"
      },
      "yesChainEventId": "cevre_protestolari",
      "noChainEventId": null,
      "imagePath": "assets/events/Canal Istanbul Project.jpeg",
      "sequence": 28,
      "isNeutralEvent": false
    },
    {
      "id": "zeytin_dali_harekati",
      "title": "Zeytin Dalı Harekatı",
      "description": "Suriye'nin Afrin bölgesindeki YPG/PKK unsurlarına karşı askeri operasyon başlatma planları hazır. Operasyonu onaylayacak mısınız?",
      "era": "kriz_ve_tepki",
      "yesImpact": {
        "health": -10,
        "wealth": -10,
        "political": 20,
        "communal": 15,
        "optionText": "Terör koridoruna izin vermeyeceğiz"
      },
      "noImpact": {
        "health": 0,
        "wealth": 5,
        "political": -15,
        "communal": -10,
        "optionText": "Uluslararası tepkilerden kaçınmalıyız"
      },
      "yesChainEventId": "abd_turkiye_gerginligi",
      "noChainEventId": null,
      "imagePath": "assets/events/Olive Branch Operation.jpeg",
      "sequence": 24,
      "isNeutralEvent": false
    },
    {
      "id": "rusya_ile_yakinlasma",
      "title": "Rusya ile Yakınlaşma",
      "description": "Batı ile ilişkiler gerginleşirken, Rusya ile daha yakın ilişkiler kurma fırsatı doğuyor. Rusya ile stratejik ortaklığı derinleştirecek misiniz?",
      "era": "kriz_ve_tepki",
      "yesImpact": {
        "health": 0,
        "wealth": 10,
        "political": 15,
        "communal": 5,
        "optionText": "Çok kutuplu bir dünyada farklı ortaklıklar kurmalıyız"
      },
      "noImpact": {
        "health": 0,
        "wealth": -5,
        "political": -10,
        "communal": 0,
        "optionText": "NATO müttefiklerimizle ilişkilerimize odaklanmalıyız"
      },
      "yesChainEventId": "nato_uyeliginde_gerginlik",
      "noChainEventId": null,
      "imagePath": "assets/events/Russia Rapprochement.jpeg",
      "sequence": 25,
      "isNeutralEvent": false
    },
    {
      "id": "uluslararasi_yaptirimlar",
      "title": "Uluslararası Yaptırımlar",
      "description": "Barış Pınarı Harekatı nedeniyle AB ve ABD'den yaptırım tehditleri geliyor. Operasyona devam edecek misiniz?",
      "era": "kriz_ve_tepki",
      "yesImpact": {
        "health": -5,
        "wealth": -20,
        "political": 15,
        "communal": 10,
        "optionText": "Ulusal güvenliğimizden taviz vermeyeceğiz"
      },
      "noImpact": {
        "health": 0,
        "wealth": 15,
        "political": -15,
        "communal": -10,
        "optionText": "Ateşkes ilan edip diplomatik çözüm arayacağız"
      },
      "yesChainEventId": null,
      "noChainEventId": null,
      "imagePath": "assets/events/International Sanctions.jpeg",
      "sequence": 24,
      "isNeutralEvent": false
    },
    {
      "id": "f35_programindan_cikarilma",
      "title": "F-35 Programından Çıkarılma",
      "description": "S-400 alımı nedeniyle ABD, Türkiye'yi F-35 programından çıkardı. Alternatif savaş uçağı projesine başlayacak mısınız?",
      "era": "kriz_ve_tepki",
      "yesImpact": {
        "health": 0,
        "wealth": -20,
        "political": 15,
        "communal": 10,
        "optionText": "Milli savaş uçağı projemizi hızlandıracağız"
      },
      "noImpact": {
        "health": 0,
        "wealth": -10,
        "political": -15,
        "communal": -5,
        "optionText": "ABD ile uzlaşma arayacağız"
      },
      "yesChainEventId": null,
      "noChainEventId": null,
      "imagePath": "assets/events/F-35 Program Removal.jpeg",
      "sequence": 27,
      "isNeutralEvent": false
    },
    {
      "id": "yatirimci_guven_kaybi",
      "title": "Yatırımcı Güven Kaybı",
      "description": "Merkez Bankası Başkanı'nın değiştirilmesi uluslararası yatırımcıların güvenini sarstı. Piyasaları sakinleştirmek için adım atacak mısınız?",
      "era": "kriz_ve_tepki",
      "yesImpact": {
        "health": 0,
        "wealth": 15,
        "political": -10,
        "communal": 0,
        "optionText": "Ekonomik reform paketi açıklayacağız"
      },
      "noImpact": {
        "health": 0,
        "wealth": -20,
        "political": 10,
        "communal": -5,
        "optionText": "Kendi ekonomi politikalarımızda ısrar edeceğiz"
      },
      "yesChainEventId": null,
      "noChainEventId": null,
      "imagePath": "assets/events/Investor Confidence Loss.jpeg",
      "sequence": 29,
      "isNeutralEvent": false
    },
    {
      "id": "ab_yaptirimlari",
      "title": "AB Yaptırımları",
      "description": "Doğu Akdeniz'deki faaliyetleriniz nedeniyle AB yaptırım kararı aldı. Tutumunuzu değiştirecek misiniz?",
      "era": "kriz_ve_tepki",
      "yesImpact": {
        "health": 0,
        "wealth": 15,
        "political": -15,
        "communal": -10,
        "optionText": "AB ile ilişkilerimizi korumak için geri adım atacağız"
      },
      "noImpact": {
        "health": 0,
        "wealth": -20,
        "political": 15,
        "communal": 10,
        "optionText": "Egemenlik haklarımızdan taviz vermeyeceğiz"
      },
      "yesChainEventId": null,
      "noChainEventId": null,
      "imagePath": "assets/events/EU Sanctions.jpeg",
      "sequence": 30,
      "isNeutralEvent": false
    },
    {
      "id": "uluslararasi_insan_haklari_elestirisi",
      "title": "Uluslararası İnsan Hakları Eleştirisi",
      "description": "OHAL uygulamaları nedeniyle uluslararası insan hakları örgütleri Türkiye'yi eleştiriyor. Bu eleştirilere nasıl yanıt vereceksiniz?",
      "era": "kriz_ve_tepki",
      "yesImpact": {
        "health": 5,
        "wealth": 10,
        "political": -10,
        "communal": 5,
        "optionText": "Bazı OHAL uygulamalarını yumuşatacağız"
      },
      "noImpact": {
        "health": -5,
        "wealth": -5,
        "political": 15,
        "communal": -10,
        "optionText": "İç işlerimize karışılmasına izin vermeyeceğiz"
      },
      "yesChainEventId": null,
      "noChainEventId": null,
      "imagePath": "assets/events/Human Rights Criticism.jpeg",
      "sequence": 24,
      "isNeutralEvent": false
    },
    {
      "id": "ab_multeci_anlasmasi_krizi",
      "title": "AB Mülteci Anlaşması Krizi",
      "description": "Mültecilerin Avrupa'ya geçişine izin vermeniz AB ile krize yol açtı. AB, mali yardımı artırma teklifinde bulunuyor. Teklifi kabul edecek misiniz?",
      "era": "kriz_ve_tepki",
      "yesImpact": {
        "health": 5,
        "wealth": 20,
        "political": -10,
        "communal": -5,
        "optionText": "Yeni anlaşma şartlarını kabul edeceğiz"
      },
      "noImpact": {
        "health": -10,
        "wealth": -15,
        "political": 15,
        "communal": 10,
        "optionText": "Sınırları açık tutmaya devam edeceğiz"
      },
      "yesChainEventId": null,
      "noChainEventId": null,
      "imagePath": "assets/events/EU Refugee Deal Crisis.jpeg",
      "sequence": 27,
      "isNeutralEvent": false
    },
    {
      "id": "rusya_ile_gerginlik",
      "title": "Rusya ile Gerginlik",
      "description": "İdlib operasyonu Rusya ile ilişkileri gerdi. Rus destekli Suriye güçleri Türk askerlerine saldırdı. Nasıl karşılık vereceksiniz?",
      "era": "kriz_ve_tepki",
      "yesImpact": {
        "health": -15,
        "wealth": -10,
        "political": 20,
        "communal": 15,
        "optionText": "Tüm gücümüzle karşılık vereceğiz"
      },
      "noImpact": {
        "health": -5,
        "wealth": 5,
        "political": -15,
        "communal": -10,
        "optionText": "Putin ile acil görüşme talep edeceğiz"
      },
      "yesChainEventId": null,
      "noChainEventId": null,
      "imagePath": "assets/events/Russia Tension.jpeg",
      "sequence": 28,
      "isNeutralEvent": false
    },
    {
      "id": "cevre_protestolari",
      "title": "Çevre Protestoları",
      "description": "Kanal İstanbul projesi çevrecilerin ve İstanbul Büyükşehir Belediyesi'nin protestolarına yol açtı. Projeyi hızlandıracak mısınız yoksa diyalog mu kuracaksınız?",
      "era": "kriz_ve_tepki",
      "yesImpact": {
        "health": -5,
        "wealth": -10,
        "political": 15,
        "communal": -15,
        "optionText": "Proje ulusal öneme sahip, hızla ilerleyeceğiz"
      },
      "noImpact": {
        "health": 5,
        "wealth": 5,
        "political": -10,
        "communal": 15,
        "optionText": "Paydaşlarla diyalog kurup endişeleri dinleyeceğiz"
      },
      "yesChainEventId": null,
      "noChainEventId": null,
      "imagePath": "assets/events/Environmental Protests.jpeg",
      "sequence": 29,
      "isNeutralEvent": false
    },
    {
      "id": "abd_turkiye_gerginligi",
      "title": "ABD-Türkiye Gerginliği",
      "description": "Afrin operasyonu ABD ile ilişkileri gerdi. ABD, YPG/PKK'ya desteğini sürdürüyor. ABD'ye karşı sert bir tutum mu alacaksınız?",
      "era": "kriz_ve_tepki",
      "yesImpact": {
        "health": 0,
        "wealth": -15,
        "political": 15,
        "communal": 10,
        "optionText": "ABD'nin terör örgütlerine desteğini kınayacağız"
      },
      "noImpact": {
        "health": 0,
        "wealth": 10,
        "political": -10,
        "communal": -5,
        "optionText": "Stratejik ortaklığımızı korumaya çalışacağız"
      },
      "yesChainEventId": null,
      "noChainEventId": null,
      "imagePath": "assets/events/US Turkey Tension.jpeg",
      "sequence": 25,
      "isNeutralEvent": false
    },
    {
      "id": "nato_uyeliginde_gerginlik",
      "title": "NATO Üyeliğinde Gerginlik",
      "description": "Rusya ile yakınlaşmanız NATO müttefiklerinizle gerginliğe yol açtı. NATO tatbikatlarına katılım konusunda nasıl bir tutum alacaksınız?",
      "era": "kriz_ve_tepki",
      "yesImpact": {
        "health": 0,
        "wealth": 10,
        "political": -15,
        "communal": -5,
        "optionText": "NATO taahhütlerimize bağlı kalacağız"
      },
      "noImpact": {
        "health": 0,
        "wealth": -10,
        "political": 15,
        "communal": 10,
        "optionText": "Bazı tatbikatlara katılmayı reddederek tepkimizi göstereceğiz"
      },
      "yesChainEventId": null,
      "noChainEventId": null,
      "imagePath": "assets/events/NATO Membership Tension.jpeg",
      "sequence": 26,
      "isNeutralEvent": false
    },
    {
      "id": "sinir_guvenligi_tehdidi",
      "title": "Sınır Güvenliği Tehdidi",
      "description": "Suriye sınırında terör tehdidi artıyor. Askeri operasyon yapmama kararınız eleştiriliyor. Sınır güvenliği için alternatif bir plan sunacak mısınız?",
      "era": "kriz_ve_tepki",
      "yesImpact": {
        "health": 0,
        "wealth": -10,
        "political": 10,
        "communal": 5,
        "optionText": "Sınır duvarı inşaatını hızlandıracağız"
      },
      "noImpact": {
        "health": -10,
        "wealth": 0,
        "political": -15,
        "communal": -10,
        "optionText": "Mevcut güvenlik önlemleri yeterli"
      },
      "yesChainEventId": null,
      "noChainEventId": null,
      "imagePath": "assets/events/Border Security Threat.jpeg",
      "sequence": 24,
      "isNeutralEvent": false
    },
    {
      "id": "gozlem_noktalari_kaybi",
      "title": "Gözlem Noktaları Kaybı",
      "description": "İdlib'de müdahale etmeme kararınız sonrası Türk gözlem noktaları Suriye rejim güçleri tarafından kuşatıldı. Askerlerimizi geri çekecek misiniz?",
      "era": "kriz_ve_tepki",
      "yesImpact": {
        "health": 5,
        "wealth": 5,
        "political": -20,
        "communal": -15,
        "optionText": "Askerlerimizin güvenliği için geri çekeceğiz"
      },
      "noImpact": {
        "health": -15,
        "wealth": -10,
        "political": 10,
        "communal": 5,
        "optionText": "Gözlem noktalarını korumak için direnmeye devam edeceğiz"
      },
      "yesChainEventId": null,
      "noChainEventId": null,
      "imagePath": "assets/events/Observation Posts Loss.jpeg",
      "sequence": 28,
      "isNeutralEvent": false
    },
    {
      "id": "abd_iliskileri_iyilesme",
      "title": "ABD İlişkileri İyileşme",
      "description": "Rahip Brunson'ı serbest bırakmanız ABD ile ilişkilerde yumuşamaya yol açtı. ABD ile yeni bir stratejik diyalog başlatacak mısınız?",
      "era": "kriz_ve_tepki",
      "yesImpact": {
        "health": 0,
        "wealth": 15,
        "political": 10,
        "communal": -5,
        "optionText": "ABD ile ilişkilerimizi güçlendireceğiz"
      },
      "noImpact": {
        "health": 0,
        "wealth": -5,
        "political": 5,
        "communal": 10,
        "optionText": "Temkinli yaklaşmaya devam edeceğiz"
      },
      "yesChainEventId": null,
      "noChainEventId": null,
      "imagePath": "assets/events/US Relations Improvement.jpeg",
      "sequence": 25,
      "isNeutralEvent": false
    },
    {
      "id": "abd_yaptirimlari",
      "title": "ABD Yaptırımları",
      "description": "ABD, Rahip Brunson'ın tutukluluğu nedeniyle Türkiye'ye ekonomik yaptırımlar uyguluyor. Türk Lirası değer kaybediyor. Karşı yaptırımlar uygulayacak mısınız?",
      "era": "kriz_ve_tepki",
      "yesImpact": {
        "health": 0,
        "wealth": -15,
        "political": 15,
        "communal": 10,
        "optionText": "Biz de ABD ürünlerine boykot uygulayacağız"
      },
      "noImpact": {
        "health": 0,
        "wealth": -10,
        "political": -10,
        "communal": -5,
        "optionText": "Diplomatik kanallardan çözüm arayacağız"
      },
      "yesChainEventId": null,
      "noChainEventId": null,
      "imagePath": "assets/events/US Sanctions.jpeg",
      "sequence": 25,
      "isNeutralEvent": false
    },
    {
      "id": "darbe_girisimi",
      "title": "Darbe Girişimi",
      "description": "Askeri bir darbe girişimi başladı! Ordu birlikleri sokaklarda ve savaş uçakları Ankara üzerinde uçuyor. Vatandaşları direnmeye ve sokaklara çıkmaya çağıracak mısınız?",
      "era": "kriz_ve_tepki",
      "yesImpact": {
        "health": -15,
        "wealth": 0,
        "political": 25,
        "communal": 20,
        "optionText": "Tüm vatandaşları direnmeye çağırıyorum"
      },
      "noImpact": {
        "health": 0,
        "wealth": 0,
        "political": -50,
        "communal": -50,
        "optionText": "Darbe liderleriyle müzakere edeceğim"
      },
      "yesChainEventId": "darbe_sonrasi_tasfiye",
      "noChainEventId": null,
      "imagePath": "assets/events/Coup Attempt.jpeg",
      "sequence": 21
    },
    {
      "id": "darbe_sonrasi_tasfiye",
      "title": "Darbe Sonrası Tasfiye",
      "description": "Başarısız darbe girişiminden sonra, şüpheli Gülen destekçilerinin devlet kurumlarından tasfiye edilmesi çağrıları var. Tasfiye ne kadar geniş olmalı?",
      "era": "kriz_ve_tepki",
      "yesImpact": {
        "health": 0,
        "wealth": -10,
        "political": 20,
        "communal": -15,
        "optionText": "Tüm şüpheli Gülencileri uzaklaştırın"
      },
      "noImpact": {
        "health": 0,
        "wealth": 0,
        "political": -15,
        "communal": 10,
        "optionText": "Sadece açık kanıtı olanları hedefleyin"
      },
      "yesChainEventId": "ohal_durumu",
      "noChainEventId": null,
      "imagePath": "assets/events/Post-Coup Purge.jpeg",
      "sequence": 22
    },
    {
      "id": "anayasa_referandumu",
      "title": "Anayasa Referandumu",
      "description": "Başkanlık sistemi oluşturmak için anayasayı değiştirme fırsatınız var. Bu referandum için bastıracak mısınız?",
      "era": "kriz_ve_tepki",
      "yesImpact": {
        "health": 0,
        "wealth": 0,
        "political": 25,
        "communal": -15,
        "optionText": "Türkiye'nin güçlü bir başkanlık sistemine ihtiyacı var"
      },
      "noImpact": {
        "health": 0,
        "wealth": 0,
        "political": -20,
        "communal": 10,
        "optionText": "Parlamenter sistem Türkiye'ye iyi hizmet ediyor"
      },
      "yesChainEventId": "baskanlik_yetkileri",
      "noChainEventId": null,
      "imagePath": "assets/events/Constitutional Referendum.jpeg",
      "sequence": 25
    },
    {
      "id": "doviz_krizi",
      "title": "Döviz Krizi",
      "description": "Türk lirası değer kaybediyor. Merkez Bankası faiz oranlarını yükseltmeyi öneriyor. Bunu yapmalarına izin verecek misiniz?",
      "era": "kriz_ve_tepki",
      "yesImpact": {
        "health": 0,
        "wealth": 20,
        "political": -15,
        "communal": -10,
        "optionText": "Merkez Bankası gerekli önlemleri almalı"
      },
      "noImpact": {
        "health": 0,
        "wealth": -25,
        "political": 10,
        "communal": -5,
        "optionText": "Faiz, her kötülüğün anasıdır"
      },
      "yesChainEventId": "ekonomik_iyilesme",
      "noChainEventId": "enflasyon_sarmal",
      "imagePath": "assets/events/Currency Crisis.jpeg",
      "sequence": 27
    },
    {
      "id": "muhalefet_belediye_baskani",
      "title": "Muhalefet Belediye Başkanı",
      "description": "Muhalefet adayı İstanbul belediye başkanlığı seçimini dar bir farkla kazandı. Seçimin yenilenmesini talep edecek misiniz?",
      "era": "gec_donem",
      "yesImpact": {
        "health": 0,
        "wealth": 0,
        "political": 10,
        "communal": -15,
        "optionText": "Usulsüzlükler vardı"
      },
      "noImpact": {
        "health": 0,
        "wealth": 0,
        "political": -15,
        "communal": 10,
        "optionText": "Seçmenlerin iradesine saygı duyuyoruz"
      },
      "yesChainEventId": "secim_yenileme",
      "noChainEventId": null,
      "imagePath": "assets/events/Opposition Mayor.jpeg",
      "sequence": 30
    },
    {
      "id": "ayasofya",
      "title": "Ayasofya",
      "description": "Ayasofya'nın müzeden camiye dönüştürülmesi çağrıları var. Bu dönüşümü destekleyecek misiniz?",
      "era": "gec_donem",
      "yesImpact": {
        "health": 0,
        "wealth": -5,
        "political": 15,
        "communal": 5,
        "optionText": "Ayasofya cami statüsüne geri dönmeli"
      },
      "noImpact": {
        "health": 0,
        "wealth": 5,
        "political": -10,
        "communal": -5,
        "optionText": "Tüm insanlık için müze olarak kalmalı"
      },
      "yesChainEventId": "uluslararasi_dini_elestiri",
      "noChainEventId": null,
      "imagePath": "assets/events/Hagia Sophia.jpeg",
      "sequence": 31
    },
    {
      "id": "medya_duzenlemesi",
      "title": "Medya Düzenlemesi",
      "description": "Sosyal medya platformları hükümetinizi eleştirmek için kullanılıyor. Bu platformları düzenlemek için yeni bir yasa uygulayacak mısınız?",
      "era": "gec_donem",
      "yesImpact": {
        "health": 0,
        "wealth": 0,
        "political": 15,
        "communal": -20,
        "optionText": "Vatandaşlarımızı zararlı içerikten korumalıyız"
      },
      "noImpact": {
        "health": 0,
        "wealth": 0,
        "political": -15,
        "communal": 10,
        "optionText": "Çevrimiçi ifade özgürlüğüne saygı duyacağız"
      },
      "yesChainEventId": "uluslararasi_basin_ozgurlugu_elestirisi",
      "noChainEventId": null,
      "imagePath": "assets/events/Media Regulation.jpeg",
      "sequence": 33
    },
    {
      "id": "ekonomik_ortodoksluk",
      "title": "Ekonomik Ortodoksluk",
      "description": "Enflasyon rekor seviyelere ulaştı. Ekonomik danışmanlar ortodoks ekonomi politikalarına dönmeyi öneriyor. Kilit pozisyonlara geleneksel ekonomistler atayacak mısınız?",
      "era": "gec_donem",
      "yesImpact": {
        "health": 0,
        "wealth": 25,
        "political": -10,
        "communal": -5,
        "optionText": "Deneyimli ekonomistlere ihtiyacımız var"
      },
      "noImpact": {
        "health": 0,
        "wealth": -30,
        "political": 5,
        "communal": -10,
        "optionText": "Benzersiz ekonomik modelimizle devam edeceğiz"
      },
      "yesChainEventId": null,
      "noChainEventId": null,
      "imagePath": "assets/events/Economic Orthodoxy.jpeg",
      "sequence": 34
    },
    {
      "id": "deprem_felaketi",
      "title": "Deprem Felaketi",
      "description": "Türkiye'yi yıkıcı bir deprem vurdu. Binlerce kişi enkaz altında. Uluslararası yardımı kabul edecek misiniz?",
      "era": "iktidara_yukselis",
      "yesImpact": {
        "health": 20,
        "wealth": 10,
        "political": -5,
        "communal": 15,
        "optionText": "Tüm uluslararası yardımı memnuniyetle karşılıyoruz"
      },
      "noImpact": {
        "health": -20,
        "wealth": -15,
        "political": 5,
        "communal": -25,
        "optionText": "Türkiye bununla tek başına başa çıkabilecek kadar güçlü"
      },
      "yesChainEventId": "yeniden_yapilanma_cabalar",
      "noChainEventId": null,
      "imagePath": "assets/events/Earthquake Disaster.jpeg",
      "sequence": 6
    },
    {
      "id": "teror_saldirisi",
      "title": "Terör Saldırısı",
      "description": "İstanbul'da büyük bir terör saldırısı gerçekleşti. Genişletilmiş yetkilerle olağanüstü hal ilan edecek misiniz?",
      "era": "konsolidasyon",
      "yesImpact": {
        "health": 10,
        "wealth": 0,
        "political": 15,
        "communal": -10,
        "optionText": "Güvenliği sağlamak için özel yetkilere ihtiyacımız var"
      },
      "noImpact": {
        "health": -10,
        "wealth": 0,
        "political": -10,
        "communal": 5,
        "optionText": "Normal yasal çerçeve içinde yanıt vereceğiz"
      },
      "yesChainEventId": "guvenlik_sertlestirme",
      "noChainEventId": null,
      "imagePath": "assets/events/Terrorist Attack.jpeg",
      "sequence": 18
    },
    {
      "id": "pandemi_yaniti",
      "title": "Pandemi Yanıtı",
      "description": "Küresel bir pandemi Türkiye'ye ulaştı. Sıkı karantina önlemleri uygulayacak mısınız?",
      "era": "gec_donem",
      "yesImpact": {
        "health": 20,
        "wealth": -20,
        "political": -5,
        "communal": -10,
        "optionText": "Halk sağlığı en büyük önceliğimizdir"
      },
      "noImpact": {
        "health": -25,
        "wealth": 10,
        "political": 5,
        "communal": 5,
        "optionText": "Ekonomiyi kapatamayız"
      },
      "yesChainEventId": null,
      "noChainEventId": null,
      "imagePath": "assets/events/Pandemic Response.jpeg",
      "sequence": 32
    },
    {
      "id": "aile_yemegi",
      "title": "Aile Yemeği",
      "description": "Yoğun programınız arasında ailenizle yemek yemeye vakit ayırabilecek misiniz?",
      "era": "iktidara_yukselis",
      "isNeutralEvent": true,
      "yesImpact": {
        "health": 5,
        "wealth": 0,
        "political": -5,
        "communal": 5,
        "optionText": "Aile her şeyden önemlidir"
      },
      "noImpact": {
        "health": -5,
        "wealth": 0,
        "political": 5,
        "communal": -5,
        "optionText": "Ülke meseleleri önceliklidir"
      },
      "yesChainEventId": null,
      "noChainEventId": null,
      "imagePath": "assets/events/Family Dinner.jpeg",
      "sequence": 500
    },
    {
      "id": "cay_sohbeti",
      "title": "Çay Sohbeti",
      "description": "Yerel bir çayhanede vatandaşlarla sohbet etmek için davet aldınız. Katılacak mısınız?",
      "era": "konsolidasyon",
      "isNeutralEvent": true,
      "yesImpact": {
        "health": 0,
        "wealth": 0,
        "political": 5,
        "communal": 10,
        "optionText": "Halkın nabzını tutmak önemli"
      },
      "noImpact": {
        "health": 0,
        "wealth": 0,
        "political": -5,
        "communal": -5,
        "optionText": "Güvenlik riski çok yüksek"
      },
      "yesChainEventId": null,
      "noChainEventId": null,
      "imagePath": "assets/events/Tea Conversation.jpeg",
      "sequence": 500
    },
    {
      "id": "cami_ziyareti",
      "title": "Cami Ziyareti",
      "description": "Cuma namazı için önemli bir camide görünmeniz isteniyor. Katılacak mısınız?",
      "era": "konsolidasyon",
      "isNeutralEvent": true,
      "yesImpact": {
        "health": 0,
        "wealth": 0,
        "political": 5,
        "communal": 10,
        "optionText": "Dini vecibelerimi yerine getirmeliyim"
      },
      "noImpact": {
        "health": 0,
        "wealth": 0,
        "political": -5,
        "communal": -5,
        "optionText": "Özel bir toplantım var"
      },
      "yesChainEventId": null,
      "noChainEventId": null,
      "imagePath": "assets/events/Mosque Visit.jpeg",
      "sequence": 500
    },
    {
      "id": "futbol_maci",
      "title": "Futbol Maçı",
      "description": "Önemli bir futbol maçına davet edildiniz. Stadyumda görünecek misiniz?",
      "era": "kriz_ve_tepki",
      "isNeutralEvent": true,
      "yesImpact": {
        "health": 5,
        "wealth": 0,
        "political": 0,
        "communal": 10,
        "optionText": "Milli takımımızı desteklemeliyim"
      },
      "noImpact": {
        "health": 0,
        "wealth": 0,
        "political": 0,
        "communal": -5,
        "optionText": "Daha önemli işlerim var"
      },
      "yesChainEventId": null,
      "noChainEventId": null,
      "imagePath": "assets/events/Football Match.jpeg",
      "sequence": 500
    },
    {
      "id": "kitap_okuma",
      "title": "Kitap Okuma",
      "description": "Yeni çıkan bir kitap hakkında görüşünüz soruluyor. Okuyacak mısınız?",
      "era": "gec_donem",
      "isNeutralEvent": true,
      "yesImpact": {
        "health": 5,
        "wealth": 0,
        "political": 5,
        "communal": 0,
        "optionText": "Entelektüel gelişim önemlidir"
      },
      "noImpact": {
        "health": 0,
        "wealth": 0,
        "political": -5,
        "communal": 0,
        "optionText": "Okumak için vaktim yok"
      },
      "yesChainEventId": null,
      "noChainEventId": null,
      "imagePath": "assets/events/Reading a Book.jpeg",
      "sequence": 500
    },
    {
      "id": "ramazan_iftari",
      "title": "Ramazan İftarı",
      "description": "Büyük bir iftar organizasyonuna ev sahipliği yapmanız isteniyor. Kabul edecek misiniz?",
      "era": "kriz_ve_tepki",
      "isNeutralEvent": true,
      "yesImpact": {
        "health": 0,
        "wealth": -5,
        "political": 5,
        "communal": 15,
        "optionText": "Bu kutsal ayda halkla bir araya gelmeliyim"
      },
      "noImpact": {
        "health": 0,
        "wealth": 0,
        "political": -5,
        "communal": -10,
        "optionText": "Özel programım var"
      },
      "yesChainEventId": null,
      "noChainEventId": null,
      "imagePath": "assets/events/Ramadan Iftar.jpeg",
      "sequence": 500
    },
    {
      "id": "teknoloji_tanitimi",
      "title": "Teknoloji Tanıtımı",
      "description": "Yerli teknoloji şirketinin yeni ürün lansmanına katılmanız isteniyor. Gidecek misiniz?",
      "era": "gec_donem",
      "isNeutralEvent": true,
      "yesImpact": {
        "health": 0,
        "wealth": 5,
        "political": 5,
        "communal": 5,
        "optionText": "Yerli teknolojiye destek vermeliyiz"
      },
      "noImpact": {
        "health": 0,
        "wealth": -5,
        "political": -5,
        "communal": 0,
        "optionText": "Daha önemli konulara odaklanmalıyım"
      },
      "yesChainEventId": null,
      "noChainEventId": null,
      "imagePath": "assets/events/Technology Presentation.jpeg",
      "sequence": 500
    },
    {
      "id": "aile_tatili",
      "title": "Aile Tatili",
      "description": "Aileniz kısa bir tatil için size baskı yapıyor. Birkaç günlüğüne işten uzaklaşacak mısınız?",
      "era": "gec_donem",
      "isNeutralEvent": true,
      "yesImpact": {
        "health": 10,
        "wealth": 0,
        "political": -5,
        "communal": 0,
        "optionText": "Dinlenmek beni daha verimli yapacak"
      },
      "noImpact": {
        "health": -5,
        "wealth": 0,
        "political": 5,
        "communal": -5,
        "optionText": "Ülke meseleleri tatilden daha önemli"
      },
      "yesChainEventId": null,
      "noChainEventId": null,
      "imagePath": "assets/events/Family Vacation.jpeg",
      "sequence": 500
    }
  ]
}